ag_lbpt/__init__.py
ag_lbpt/ag.py
ag_lbpt/util.py
ag_lbpt-1.0.0.dist-info/METADATA
ag_lbpt-1.0.0.dist-info/WHEEL
ag_lbpt-1.0.0.dist-info/top_level.txt
ag_lbpt-1.0.0.dist-info/RECORD
