Metadata-Version: 2.1
Name: ag_lbpt
Version: 1.0.0
Summary: Algoritmo Genético
Author: Luis Beltran Palma Ttito
Author-email: luis.palma@unsaac.edu.pe
License: GPL
Requires-Dist: folium
Requires-Dist: networkx
